{"api_version":"1.0","fname":"invoice-3-3_h2zc224n.jiv_2026-07-22-14-24-133.pdf","original_fname":"invoice-3-3_h2zc224n.jiv.pdf","fields":{"name":"Neid","vendor-addr":"Gillitzerstrasse 10, Rosenheim, BY, 83022","billing-name":"Zuuf AG","billing-addr":"Domsdorfer Kirchweg 14 Forst, BRB, 03149","billing-vat-no":"","shipping-addr":"","payment-addr":"","vendor-vat-no":"","date":"2021-12-22","due-date":"","invoice-no":"4405","po-no":"","payment-terms":"","shipping-charges":"","tax":"","net-amount":"","total":"","discount":""},"multi_valued_fields":{},"items":[{"instance":1,"values":{"line-no":"Nissan/Frontier","description":"146-53-6874","item-po-no":"33600","quantity":"","unit-price":"","line-amount":"","part-no":""}},{"instance":2,"values":{"line-no":"Country of origin: France Color: Red","description":"","item-po-no":"","quantity":"","unit-price":"","line-amount":"","part-no":""}}],"pages":[{"page_rotation":0,"page_no":0,"width":612.0,"height":792.0,"words":[{"description":"Neid","boundingPoly":{"vertices":[{"x":108.02,"y":59.1},{"x":149.01,"y":59.1},{"x":149.01,"y":76.34},{"x":108.02,"y":76.34}]},"line":0,"tag":"name"},{"description":"NEID","boundingPoly":{"vertices":[{"x":482.3,"y":67.93},{"x":536.7,"y":67.93},{"x":536.7,"y":87.4},{"x":482.3,"y":87.4}]},"line":1,"tag":""},{"description":"Gillitzerstrasse","boundingPoly":{"vertices":[{"x":108.02,"y":81.59},{"x":164.8,"y":81.59},{"x":164.8,"y":90.72},{"x":108.02,"y":90.72}]},"line":2,"tag":"vendor-addr"},{"description":"10,","boundingPoly":{"vertices":[{"x":167.35,"y":81.59},{"x":178.88,"y":81.59},{"x":178.88,"y":90.72},{"x":167.35,"y":90.72}]},"line":2,"tag":"vendor-addr"},{"description":"Rosenheim,","boundingPoly":{"vertices":[{"x":181.37,"y":81.59},{"x":227.08,"y":81.59},{"x":227.08,"y":90.72},{"x":181.37,"y":90.72}]},"line":2,"tag":"vendor-addr"},{"description":"BY,","boundingPoly":{"vertices":[{"x":229.69,"y":81.59},{"x":244.58,"y":81.59},{"x":244.58,"y":90.72},{"x":229.69,"y":90.72}]},"line":2,"tag":"vendor-addr"},{"description":"83022","boundingPoly":{"vertices":[{"x":247.07,"y":81.59},{"x":270.46,"y":81.59},{"x":270.46,"y":90.72},{"x":247.07,"y":90.72}]},"line":2,"tag":"vendor-addr"},{"description":"Date","boundingPoly":{"vertices":[{"x":108.02,"y":129.71},{"x":132.14,"y":129.71},{"x":132.14,"y":139.25},{"x":108.02,"y":139.25}]},"line":3,"tag":""},{"description":"December","boundingPoly":{"vertices":[{"x":108.02,"y":144.35},{"x":148.51,"y":144.35},{"x":148.51,"y":153.48},{"x":108.02,"y":153.48}]},"line":4,"tag":"date"},{"description":"22,","boundingPoly":{"vertices":[{"x":151.05,"y":144.35},{"x":162.57,"y":144.35},{"x":162.57,"y":153.48},{"x":151.05,"y":153.48}]},"line":4,"tag":"date"},{"description":"2021","boundingPoly":{"vertices":[{"x":165.06,"y":144.35},{"x":183.78,"y":144.35},{"x":183.78,"y":153.48},{"x":165.06,"y":153.48}]},"line":4,"tag":"date"},{"description":"Instructions","boundingPoly":{"vertices":[{"x":108.02,"y":201.23},{"x":161.06,"y":201.23},{"x":161.06,"y":210.77},{"x":108.02,"y":210.77}]},"line":7,"tag":""},{"description":"None","boundingPoly":{"vertices":[{"x":108.02,"y":215.87},{"x":129.93,"y":215.87},{"x":129.93,"y":225.0},{"x":108.02,"y":225.0}]},"line":8,"tag":""},{"description":"Make/Model","boundingPoly":{"vertices":[{"x":108.02,"y":248.66},{"x":171.13,"y":248.66},{"x":171.13,"y":258.2},{"x":108.02,"y":258.2}]},"line":9,"tag":""},{"description":"Product","boundingPoly":{"vertices":[{"x":324.05,"y":248.66},{"x":361.22,"y":248.66},{"x":361.22,"y":258.2},{"x":324.05,"y":258.2}]},"line":9,"tag":""},{"description":"Code","boundingPoly":{"vertices":[{"x":363.98,"y":248.66},{"x":391.09,"y":248.66},{"x":391.09,"y":258.2},{"x":363.98,"y":258.2}]},"line":9,"tag":""},{"description":"Unit","boundingPoly":{"vertices":[{"x":499.18,"y":248.66},{"x":516.91,"y":248.66},{"x":516.91,"y":258.2},{"x":499.18,"y":258.2}]},"line":9,"tag":""},{"description":"Price","boundingPoly":{"vertices":[{"x":519.72,"y":248.66},{"x":543.68,"y":248.66},{"x":543.68,"y":258.2},{"x":519.72,"y":258.2}]},"line":9,"tag":""},{"description":"Mercury/Villager","boundingPoly":{"vertices":[{"x":100.82,"y":263.93},{"x":176.74,"y":263.93},{"x":176.74,"y":274.97},{"x":100.82,"y":274.97}]},"line":10,"tag":""},{"description":"203-64-6102","boundingPoly":{"vertices":[{"x":316.85,"y":263.93},{"x":373.82,"y":263.93},{"x":373.82,"y":274.97},{"x":316.85,"y":274.97}]},"line":10,"tag":""},{"description":"38700","boundingPoly":{"vertices":[{"x":523.18,"y":263.93},{"x":551.08,"y":263.93},{"x":551.08,"y":274.97},{"x":523.18,"y":274.97}]},"line":10,"tag":""},{"description":"Country","boundingPoly":{"vertices":[{"x":109.82,"y":276.74},{"x":136.42,"y":276.74},{"x":136.42,"y":284.78},{"x":109.82,"y":284.78}]},"line":11,"tag":""},{"description":"of","boundingPoly":{"vertices":[{"x":138.26,"y":276.74},{"x":145.12,"y":276.74},{"x":145.12,"y":284.78},{"x":138.26,"y":284.78}]},"line":11,"tag":""},{"description":"origin:","boundingPoly":{"vertices":[{"x":146.9,"y":276.74},{"x":168.29,"y":276.74},{"x":168.29,"y":284.78},{"x":146.9,"y":284.78}]},"line":11,"tag":""},{"description":"Italy","boundingPoly":{"vertices":[{"x":170.06,"y":276.74},{"x":184.02,"y":276.74},{"x":184.02,"y":284.78},{"x":170.06,"y":284.78}]},"line":11,"tag":""},{"description":" ","boundingPoly":{"vertices":[{"x":0.0,"y":0.0},{"x":0.0,"y":0.0},{"x":0.0,"y":0.0},{"x":0.0,"y":0.0}]},"line":-1,"tag":""},{"description":" ","boundingPoly":{"vertices":[{"x":0.0,"y":0.0},{"x":0.0,"y":0.0},{"x":0.0,"y":0.0},{"x":0.0,"y":0.0}]},"line":-1,"tag":""},{"description":"Color:","boundingPoly":{"vertices":[{"x":109.82,"y":286.58},{"x":129.77,"y":286.58},{"x":129.77,"y":294.62},{"x":109.82,"y":294.62}]},"line":12,"tag":""},{"description":"Silver","boundingPoly":{"vertices":[{"x":131.66,"y":286.58},{"x":149.35,"y":286.58},{"x":149.35,"y":294.62},{"x":131.66,"y":294.62}]},"line":12,"tag":""},{"description":" ","boundingPoly":{"vertices":[{"x":0.0,"y":0.0},{"x":0.0,"y":0.0},{"x":0.0,"y":0.0},{"x":0.0,"y":0.0}]},"line":-1,"tag":""},{"description":" ","boundingPoly":{"vertices":[{"x":0.0,"y":0.0},{"x":0.0,"y":0.0},{"x":0.0,"y":0.0},{"x":0.0,"y":0.0}]},"line":-1,"tag":""},{"description":"Ford/Econoline","boundingPoly":{"vertices":[{"x":100.82,"y":297.41},{"x":169.29,"y":297.41},{"x":169.29,"y":308.45},{"x":100.82,"y":308.45}]},"line":13,"tag":""},{"description":"E350","boundingPoly":{"vertices":[{"x":171.82,"y":297.41},{"x":193.84,"y":297.41},{"x":193.84,"y":308.45},{"x":171.82,"y":308.45}]},"line":13,"tag":""},{"description":"414-85-4593","boundingPoly":{"vertices":[{"x":316.85,"y":297.41},{"x":373.82,"y":297.41},{"x":373.82,"y":308.45},{"x":316.85,"y":308.45}]},"line":13,"tag":""},{"description":"35700","boundingPoly":{"vertices":[{"x":523.18,"y":297.41},{"x":551.08,"y":297.41},{"x":551.08,"y":308.45},{"x":523.18,"y":308.45}]},"line":13,"tag":""},{"description":"Country","boundingPoly":{"vertices":[{"x":109.82,"y":310.22},{"x":136.42,"y":310.22},{"x":136.42,"y":318.26},{"x":109.82,"y":318.26}]},"line":14,"tag":""},{"description":"of","boundingPoly":{"vertices":[{"x":138.26,"y":310.22},{"x":145.12,"y":310.22},{"x":145.12,"y":318.26},{"x":138.26,"y":318.26}]},"line":14,"tag":""},{"description":"origin:","boundingPoly":{"vertices":[{"x":146.9,"y":310.22},{"x":168.29,"y":310.22},{"x":168.29,"y":318.26},{"x":146.9,"y":318.26}]},"line":14,"tag":""},{"description":"Germany","boundingPoly":{"vertices":[{"x":170.18,"y":310.22},{"x":199.98,"y":310.22},{"x":199.98,"y":318.26},{"x":170.18,"y":318.26}]},"line":14,"tag":""},{"description":"Color:","boundingPoly":{"vertices":[{"x":109.82,"y":320.06},{"x":129.77,"y":320.06},{"x":129.77,"y":328.1},{"x":109.82,"y":328.1}]},"line":15,"tag":""},{"description":"Red","boundingPoly":{"vertices":[{"x":131.66,"y":320.06},{"x":144.16,"y":320.06},{"x":144.16,"y":328.1},{"x":131.66,"y":328.1}]},"line":15,"tag":""},{"description":"To","boundingPoly":{"vertices":[{"x":258.05,"y":129.71},{"x":268.77,"y":129.71},{"x":268.77,"y":139.25},{"x":258.05,"y":139.25}]},"line":3,"tag":""},{"description":"Zuuf","boundingPoly":{"vertices":[{"x":258.05,"y":144.35},{"x":277.69,"y":144.35},{"x":277.69,"y":153.48},{"x":258.05,"y":153.48}]},"line":4,"tag":"billing-name"},{"description":"AG","boundingPoly":{"vertices":[{"x":280.25,"y":144.35},{"x":294.65,"y":144.35},{"x":294.65,"y":153.48},{"x":280.25,"y":153.48}]},"line":4,"tag":"billing-name"},{"description":"Domsdorfer","boundingPoly":{"vertices":[{"x":258.05,"y":155.63},{"x":306.34,"y":155.63},{"x":306.34,"y":164.76},{"x":258.05,"y":164.76}]},"line":5,"tag":"billing-addr"},{"description":"Kirchweg","boundingPoly":{"vertices":[{"x":308.88,"y":155.63},{"x":346.32,"y":155.63},{"x":346.32,"y":164.76},{"x":308.88,"y":164.76}]},"line":5,"tag":"billing-addr"},{"description":"14","boundingPoly":{"vertices":[{"x":348.81,"y":155.63},{"x":358.15,"y":155.63},{"x":358.15,"y":164.76},{"x":348.81,"y":164.76}]},"line":5,"tag":"billing-addr"},{"description":"Forst,","boundingPoly":{"vertices":[{"x":258.05,"y":166.91},{"x":280.75,"y":166.91},{"x":280.75,"y":176.04},{"x":258.05,"y":176.04}]},"line":6,"tag":"billing-addr"},{"description":"BRB,","boundingPoly":{"vertices":[{"x":283.25,"y":166.91},{"x":304.03,"y":166.91},{"x":304.03,"y":176.04},{"x":283.25,"y":176.04}]},"line":6,"tag":"billing-addr"},{"description":"03149","boundingPoly":{"vertices":[{"x":306.52,"y":166.91},{"x":329.91,"y":166.91},{"x":329.91,"y":176.04},{"x":306.52,"y":176.04}]},"line":6,"tag":"billing-addr"},{"description":"Ship","boundingPoly":{"vertices":[{"x":408.31,"y":129.71},{"x":428.16,"y":129.71},{"x":428.16,"y":139.25},{"x":408.31,"y":139.25}]},"line":3,"tag":""},{"description":"To","boundingPoly":{"vertices":[{"x":430.96,"y":129.71},{"x":441.69,"y":129.71},{"x":441.69,"y":139.25},{"x":430.96,"y":139.25}]},"line":3,"tag":""},{"description":"Same","boundingPoly":{"vertices":[{"x":408.31,"y":144.35},{"x":429.02,"y":144.35},{"x":429.02,"y":153.48},{"x":408.31,"y":153.48}]},"line":4,"tag":""},{"description":"as","boundingPoly":{"vertices":[{"x":431.57,"y":144.35},{"x":439.28,"y":144.35},{"x":439.28,"y":153.48},{"x":431.57,"y":153.48}]},"line":4,"tag":""},{"description":"recipient","boundingPoly":{"vertices":[{"x":441.75,"y":144.35},{"x":475.22,"y":144.35},{"x":475.22,"y":153.48},{"x":441.75,"y":153.48}]},"line":4,"tag":""},{"description":"Mercury/Cougar","boundingPoly":{"vertices":[{"x":100.82,"y":330.89},{"x":174.84,"y":330.89},{"x":174.84,"y":341.93},{"x":100.82,"y":341.93}]},"line":16,"tag":""},{"description":"110-90-0753","boundingPoly":{"vertices":[{"x":316.85,"y":330.89},{"x":373.82,"y":330.89},{"x":373.82,"y":341.93},{"x":316.85,"y":341.93}]},"line":16,"tag":""},{"description":"48900","boundingPoly":{"vertices":[{"x":523.18,"y":330.89},{"x":551.08,"y":330.89},{"x":551.08,"y":341.93},{"x":523.18,"y":341.93}]},"line":16,"tag":""},{"description":"Country","boundingPoly":{"vertices":[{"x":109.82,"y":343.7},{"x":136.42,"y":343.7},{"x":136.42,"y":351.74},{"x":109.82,"y":351.74}]},"line":17,"tag":""},{"description":"of","boundingPoly":{"vertices":[{"x":138.26,"y":343.7},{"x":145.12,"y":343.7},{"x":145.12,"y":351.74},{"x":138.26,"y":351.74}]},"line":17,"tag":""},{"description":"origin:","boundingPoly":{"vertices":[{"x":146.9,"y":343.7},{"x":168.31,"y":343.7},{"x":168.31,"y":351.74},{"x":146.9,"y":351.74}]},"line":17,"tag":""},{"description":"Spain","boundingPoly":{"vertices":[{"x":170.06,"y":343.7},{"x":187.84,"y":343.7},{"x":187.84,"y":351.74},{"x":170.06,"y":351.74}]},"line":17,"tag":""},{"description":" ","boundingPoly":{"vertices":[{"x":0.0,"y":0.0},{"x":0.0,"y":0.0},{"x":0.0,"y":0.0},{"x":0.0,"y":0.0}]},"line":-1,"tag":""},{"description":" ","boundingPoly":{"vertices":[{"x":0.0,"y":0.0},{"x":0.0,"y":0.0},{"x":0.0,"y":0.0},{"x":0.0,"y":0.0}]},"line":-1,"tag":""},{"description":"Color:","boundingPoly":{"vertices":[{"x":109.82,"y":353.42},{"x":129.77,"y":353.42},{"x":129.77,"y":361.46},{"x":109.82,"y":361.46}]},"line":18,"tag":""},{"description":"Red","boundingPoly":{"vertices":[{"x":131.66,"y":353.42},{"x":144.16,"y":353.42},{"x":144.16,"y":361.46},{"x":131.66,"y":361.46}]},"line":18,"tag":""},{"description":" ","boundingPoly":{"vertices":[{"x":0.0,"y":0.0},{"x":0.0,"y":0.0},{"x":0.0,"y":0.0},{"x":0.0,"y":0.0}]},"line":-1,"tag":""},{"description":" ","boundingPoly":{"vertices":[{"x":0.0,"y":0.0},{"x":0.0,"y":0.0},{"x":0.0,"y":0.0},{"x":0.0,"y":0.0}]},"line":-1,"tag":""},{"description":"Mercedes-Benz/SL-Class","boundingPoly":{"vertices":[{"x":100.82,"y":364.37},{"x":209.92,"y":364.37},{"x":209.92,"y":375.41},{"x":100.82,"y":375.41}]},"line":19,"tag":""},{"description":"245-29-2051","boundingPoly":{"vertices":[{"x":316.85,"y":364.37},{"x":373.82,"y":364.37},{"x":373.82,"y":375.41},{"x":316.85,"y":375.41}]},"line":19,"tag":""},{"description":"10900","boundingPoly":{"vertices":[{"x":523.18,"y":364.37},{"x":551.08,"y":364.37},{"x":551.08,"y":375.41},{"x":523.18,"y":375.41}]},"line":19,"tag":""},{"description":"Country","boundingPoly":{"vertices":[{"x":109.82,"y":377.18},{"x":136.42,"y":377.18},{"x":136.42,"y":385.22},{"x":109.82,"y":385.22}]},"line":20,"tag":""},{"description":"of","boundingPoly":{"vertices":[{"x":138.26,"y":377.18},{"x":145.12,"y":377.18},{"x":145.12,"y":385.22},{"x":138.26,"y":385.22}]},"line":20,"tag":""},{"description":"origin:","boundingPoly":{"vertices":[{"x":146.9,"y":377.18},{"x":168.29,"y":377.18},{"x":168.29,"y":385.22},{"x":146.9,"y":385.22}]},"line":20,"tag":""},{"description":"Germany","boundingPoly":{"vertices":[{"x":170.18,"y":377.18},{"x":199.98,"y":377.18},{"x":199.98,"y":385.22},{"x":170.18,"y":385.22}]},"line":20,"tag":""},{"description":" ","boundingPoly":{"vertices":[{"x":0.0,"y":0.0},{"x":0.0,"y":0.0},{"x":0.0,"y":0.0},{"x":0.0,"y":0.0}]},"line":-1,"tag":""},{"description":" ","boundingPoly":{"vertices":[{"x":0.0,"y":0.0},{"x":0.0,"y":0.0},{"x":0.0,"y":0.0},{"x":0.0,"y":0.0}]},"line":-1,"tag":""},{"description":"Color:","boundingPoly":{"vertices":[{"x":109.82,"y":386.9},{"x":129.77,"y":386.9},{"x":129.77,"y":394.94},{"x":109.82,"y":394.94}]},"line":21,"tag":""},{"description":"Red","boundingPoly":{"vertices":[{"x":131.66,"y":386.9},{"x":144.16,"y":386.9},{"x":144.16,"y":394.94},{"x":131.66,"y":394.94}]},"line":21,"tag":""},{"description":" ","boundingPoly":{"vertices":[{"x":0.0,"y":0.0},{"x":0.0,"y":0.0},{"x":0.0,"y":0.0},{"x":0.0,"y":0.0}]},"line":-1,"tag":""},{"description":" ","boundingPoly":{"vertices":[{"x":0.0,"y":0.0},{"x":0.0,"y":0.0},{"x":0.0,"y":0.0},{"x":0.0,"y":0.0}]},"line":-1,"tag":""},{"description":"Acura/RL","boundingPoly":{"vertices":[{"x":100.82,"y":397.85},{"x":141.68,"y":397.85},{"x":141.68,"y":408.89},{"x":100.82,"y":408.89}]},"line":22,"tag":""},{"description":"374-97-8799","boundingPoly":{"vertices":[{"x":316.85,"y":397.85},{"x":373.82,"y":397.85},{"x":373.82,"y":408.89},{"x":316.85,"y":408.89}]},"line":22,"tag":""},{"description":"46600","boundingPoly":{"vertices":[{"x":523.18,"y":397.85},{"x":551.08,"y":397.85},{"x":551.08,"y":408.89},{"x":523.18,"y":408.89}]},"line":22,"tag":""},{"description":"Country","boundingPoly":{"vertices":[{"x":109.82,"y":410.66},{"x":136.42,"y":410.66},{"x":136.42,"y":418.7},{"x":109.82,"y":418.7}]},"line":23,"tag":""},{"description":"of","boundingPoly":{"vertices":[{"x":138.26,"y":410.66},{"x":145.12,"y":410.66},{"x":145.12,"y":418.7},{"x":138.26,"y":418.7}]},"line":23,"tag":""},{"description":"origin:","boundingPoly":{"vertices":[{"x":146.9,"y":410.66},{"x":168.29,"y":410.66},{"x":168.29,"y":418.7},{"x":146.9,"y":418.7}]},"line":23,"tag":""},{"description":"Portugal","boundingPoly":{"vertices":[{"x":170.06,"y":410.66},{"x":197.57,"y":410.66},{"x":197.57,"y":418.7},{"x":170.06,"y":418.7}]},"line":23,"tag":""},{"description":" ","boundingPoly":{"vertices":[{"x":0.0,"y":0.0},{"x":0.0,"y":0.0},{"x":0.0,"y":0.0},{"x":0.0,"y":0.0}]},"line":-1,"tag":""},{"description":" ","boundingPoly":{"vertices":[{"x":0.0,"y":0.0},{"x":0.0,"y":0.0},{"x":0.0,"y":0.0},{"x":0.0,"y":0.0}]},"line":-1,"tag":""},{"description":"Color:","boundingPoly":{"vertices":[{"x":109.82,"y":420.38},{"x":129.77,"y":420.38},{"x":129.77,"y":428.42},{"x":109.82,"y":428.42}]},"line":24,"tag":""},{"description":"Black","boundingPoly":{"vertices":[{"x":131.66,"y":420.38},{"x":148.64,"y":420.38},{"x":148.64,"y":428.42},{"x":131.66,"y":428.42}]},"line":24,"tag":""},{"description":" ","boundingPoly":{"vertices":[{"x":0.0,"y":0.0},{"x":0.0,"y":0.0},{"x":0.0,"y":0.0},{"x":0.0,"y":0.0}]},"line":-1,"tag":""},{"description":" ","boundingPoly":{"vertices":[{"x":0.0,"y":0.0},{"x":0.0,"y":0.0},{"x":0.0,"y":0.0},{"x":0.0,"y":0.0}]},"line":-1,"tag":""},{"description":"Oldsmobile/Custom","boundingPoly":{"vertices":[{"x":100.82,"y":431.35},{"x":190.16,"y":431.35},{"x":190.16,"y":442.39},{"x":100.82,"y":442.39}]},"line":25,"tag":""},{"description":"Cruiser","boundingPoly":{"vertices":[{"x":192.6,"y":431.35},{"x":224.17,"y":431.35},{"x":224.17,"y":442.39},{"x":192.6,"y":442.39}]},"line":25,"tag":""},{"description":"140-01-0079","boundingPoly":{"vertices":[{"x":316.85,"y":431.35},{"x":373.82,"y":431.35},{"x":373.82,"y":442.39},{"x":316.85,"y":442.39}]},"line":25,"tag":""},{"description":"14300","boundingPoly":{"vertices":[{"x":523.18,"y":431.35},{"x":551.08,"y":431.35},{"x":551.08,"y":442.39},{"x":523.18,"y":442.39}]},"line":25,"tag":""},{"description":"Country","boundingPoly":{"vertices":[{"x":109.82,"y":444.16},{"x":136.42,"y":444.16},{"x":136.42,"y":452.2},{"x":109.82,"y":452.2}]},"line":26,"tag":""},{"description":"of","boundingPoly":{"vertices":[{"x":138.26,"y":444.16},{"x":145.12,"y":444.16},{"x":145.12,"y":452.2},{"x":138.26,"y":452.2}]},"line":26,"tag":""},{"description":"origin:","boundingPoly":{"vertices":[{"x":146.9,"y":444.16},{"x":168.29,"y":444.16},{"x":168.29,"y":452.2},{"x":146.9,"y":452.2}]},"line":26,"tag":""},{"description":"France","boundingPoly":{"vertices":[{"x":170.06,"y":444.16},{"x":191.94,"y":444.16},{"x":191.94,"y":452.2},{"x":170.06,"y":452.2}]},"line":26,"tag":""},{"description":" ","boundingPoly":{"vertices":[{"x":0.0,"y":0.0},{"x":0.0,"y":0.0},{"x":0.0,"y":0.0},{"x":0.0,"y":0.0}]},"line":-1,"tag":""},{"description":" ","boundingPoly":{"vertices":[{"x":0.0,"y":0.0},{"x":0.0,"y":0.0},{"x":0.0,"y":0.0},{"x":0.0,"y":0.0}]},"line":-1,"tag":""},{"description":"Color:","boundingPoly":{"vertices":[{"x":109.82,"y":453.88},{"x":129.77,"y":453.88},{"x":129.77,"y":461.92},{"x":109.82,"y":461.92}]},"line":27,"tag":""},{"description":"Black","boundingPoly":{"vertices":[{"x":131.66,"y":453.88},{"x":148.64,"y":453.88},{"x":148.64,"y":461.92},{"x":131.66,"y":461.92}]},"line":27,"tag":""},{"description":" ","boundingPoly":{"vertices":[{"x":0.0,"y":0.0},{"x":0.0,"y":0.0},{"x":0.0,"y":0.0},{"x":0.0,"y":0.0}]},"line":-1,"tag":""},{"description":" ","boundingPoly":{"vertices":[{"x":0.0,"y":0.0},{"x":0.0,"y":0.0},{"x":0.0,"y":0.0},{"x":0.0,"y":0.0}]},"line":-1,"tag":""},{"description":"Buick/Skylark","boundingPoly":{"vertices":[{"x":100.82,"y":464.71},{"x":160.78,"y":464.71},{"x":160.78,"y":475.75},{"x":100.82,"y":475.75}]},"line":28,"tag":""},{"description":"462-04-7728","boundingPoly":{"vertices":[{"x":316.85,"y":464.71},{"x":373.82,"y":464.71},{"x":373.82,"y":475.75},{"x":316.85,"y":475.75}]},"line":28,"tag":""},{"description":"36000","boundingPoly":{"vertices":[{"x":523.18,"y":464.71},{"x":551.08,"y":464.71},{"x":551.08,"y":475.75},{"x":523.18,"y":475.75}]},"line":28,"tag":""},{"description":"Country","boundingPoly":{"vertices":[{"x":109.82,"y":477.52},{"x":136.42,"y":477.52},{"x":136.42,"y":485.56},{"x":109.82,"y":485.56}]},"line":29,"tag":""},{"description":"of","boundingPoly":{"vertices":[{"x":138.26,"y":477.52},{"x":145.12,"y":477.52},{"x":145.12,"y":485.56},{"x":138.26,"y":485.56}]},"line":29,"tag":""},{"description":"origin:","boundingPoly":{"vertices":[{"x":146.9,"y":477.52},{"x":168.29,"y":477.52},{"x":168.29,"y":485.56},{"x":146.9,"y":485.56}]},"line":29,"tag":""},{"description":"Germany","boundingPoly":{"vertices":[{"x":170.18,"y":477.52},{"x":199.98,"y":477.52},{"x":199.98,"y":485.56},{"x":170.18,"y":485.56}]},"line":29,"tag":""},{"description":" ","boundingPoly":{"vertices":[{"x":0.0,"y":0.0},{"x":0.0,"y":0.0},{"x":0.0,"y":0.0},{"x":0.0,"y":0.0}]},"line":-1,"tag":""},{"description":" ","boundingPoly":{"vertices":[{"x":0.0,"y":0.0},{"x":0.0,"y":0.0},{"x":0.0,"y":0.0},{"x":0.0,"y":0.0}]},"line":-1,"tag":""},{"description":"Color:","boundingPoly":{"vertices":[{"x":109.82,"y":487.36},{"x":129.77,"y":487.36},{"x":129.77,"y":495.4},{"x":109.82,"y":495.4}]},"line":30,"tag":""},{"description":"Silver","boundingPoly":{"vertices":[{"x":131.66,"y":487.36},{"x":149.35,"y":487.36},{"x":149.35,"y":495.4},{"x":131.66,"y":495.4}]},"line":30,"tag":""},{"description":" ","boundingPoly":{"vertices":[{"x":0.0,"y":0.0},{"x":0.0,"y":0.0},{"x":0.0,"y":0.0},{"x":0.0,"y":0.0}]},"line":-1,"tag":""},{"description":" ","boundingPoly":{"vertices":[{"x":0.0,"y":0.0},{"x":0.0,"y":0.0},{"x":0.0,"y":0.0},{"x":0.0,"y":0.0}]},"line":-1,"tag":""},{"description":"Mercury/Grand","boundingPoly":{"vertices":[{"x":100.82,"y":498.19},{"x":170.66,"y":498.19},{"x":170.66,"y":509.23},{"x":100.82,"y":509.23}]},"line":31,"tag":""},{"description":"Marquis","boundingPoly":{"vertices":[{"x":173.12,"y":498.19},{"x":210.12,"y":498.19},{"x":210.12,"y":509.23},{"x":173.12,"y":509.23}]},"line":31,"tag":""},{"description":"870-26-8753","boundingPoly":{"vertices":[{"x":316.85,"y":498.19},{"x":373.82,"y":498.19},{"x":373.82,"y":509.23},{"x":316.85,"y":509.23}]},"line":31,"tag":""},{"description":"28100","boundingPoly":{"vertices":[{"x":523.18,"y":498.19},{"x":551.08,"y":498.19},{"x":551.08,"y":509.23},{"x":523.18,"y":509.23}]},"line":31,"tag":""},{"description":"Country","boundingPoly":{"vertices":[{"x":109.82,"y":511.0},{"x":136.42,"y":511.0},{"x":136.42,"y":519.04},{"x":109.82,"y":519.04}]},"line":32,"tag":""},{"description":"of","boundingPoly":{"vertices":[{"x":138.26,"y":511.0},{"x":145.12,"y":511.0},{"x":145.12,"y":519.04},{"x":138.26,"y":519.04}]},"line":32,"tag":""},{"description":"origin:","boundingPoly":{"vertices":[{"x":146.9,"y":511.0},{"x":168.29,"y":511.0},{"x":168.29,"y":519.04},{"x":146.9,"y":519.04}]},"line":32,"tag":""},{"description":"Germany","boundingPoly":{"vertices":[{"x":170.18,"y":511.0},{"x":199.98,"y":511.0},{"x":199.98,"y":519.04},{"x":170.18,"y":519.04}]},"line":32,"tag":""},{"description":" ","boundingPoly":{"vertices":[{"x":0.0,"y":0.0},{"x":0.0,"y":0.0},{"x":0.0,"y":0.0},{"x":0.0,"y":0.0}]},"line":-1,"tag":""},{"description":" ","boundingPoly":{"vertices":[{"x":0.0,"y":0.0},{"x":0.0,"y":0.0},{"x":0.0,"y":0.0},{"x":0.0,"y":0.0}]},"line":-1,"tag":""},{"description":"Color:","boundingPoly":{"vertices":[{"x":109.82,"y":520.84},{"x":129.77,"y":520.84},{"x":129.77,"y":528.88},{"x":109.82,"y":528.88}]},"line":33,"tag":""},{"description":"Blue","boundingPoly":{"vertices":[{"x":131.66,"y":520.84},{"x":146.0,"y":520.84},{"x":146.0,"y":528.88},{"x":131.66,"y":528.88}]},"line":33,"tag":""},{"description":" ","boundingPoly":{"vertices":[{"x":0.0,"y":0.0},{"x":0.0,"y":0.0},{"x":0.0,"y":0.0},{"x":0.0,"y":0.0}]},"line":-1,"tag":""},{"description":" ","boundingPoly":{"vertices":[{"x":0.0,"y":0.0},{"x":0.0,"y":0.0},{"x":0.0,"y":0.0},{"x":0.0,"y":0.0}]},"line":-1,"tag":""},{"description":"BMW/M5","boundingPoly":{"vertices":[{"x":100.82,"y":531.67},{"x":145.27,"y":531.67},{"x":145.27,"y":542.71},{"x":100.82,"y":542.71}]},"line":34,"tag":""},{"description":"746-66-0334","boundingPoly":{"vertices":[{"x":316.85,"y":531.67},{"x":373.82,"y":531.67},{"x":373.82,"y":542.71},{"x":316.85,"y":542.71}]},"line":34,"tag":""},{"description":"49900","boundingPoly":{"vertices":[{"x":523.18,"y":531.67},{"x":551.08,"y":531.67},{"x":551.08,"y":542.71},{"x":523.18,"y":542.71}]},"line":34,"tag":""},{"description":"Country","boundingPoly":{"vertices":[{"x":109.82,"y":544.48},{"x":136.42,"y":544.48},{"x":136.42,"y":552.52},{"x":109.82,"y":552.52}]},"line":35,"tag":""},{"description":"of","boundingPoly":{"vertices":[{"x":138.26,"y":544.48},{"x":145.12,"y":544.48},{"x":145.12,"y":552.52},{"x":138.26,"y":552.52}]},"line":35,"tag":""},{"description":"origin:","boundingPoly":{"vertices":[{"x":146.9,"y":544.48},{"x":168.29,"y":544.48},{"x":168.29,"y":552.52},{"x":146.9,"y":552.52}]},"line":35,"tag":""},{"description":"Italy","boundingPoly":{"vertices":[{"x":170.06,"y":544.48},{"x":184.02,"y":544.48},{"x":184.02,"y":552.52},{"x":170.06,"y":552.52}]},"line":35,"tag":""},{"description":" ","boundingPoly":{"vertices":[{"x":0.0,"y":0.0},{"x":0.0,"y":0.0},{"x":0.0,"y":0.0},{"x":0.0,"y":0.0}]},"line":-1,"tag":""},{"description":" ","boundingPoly":{"vertices":[{"x":0.0,"y":0.0},{"x":0.0,"y":0.0},{"x":0.0,"y":0.0},{"x":0.0,"y":0.0}]},"line":-1,"tag":""},{"description":"Color:","boundingPoly":{"vertices":[{"x":109.82,"y":554.2},{"x":129.77,"y":554.2},{"x":129.77,"y":562.24},{"x":109.82,"y":562.24}]},"line":36,"tag":""},{"description":"Red","boundingPoly":{"vertices":[{"x":131.66,"y":554.2},{"x":144.16,"y":554.2},{"x":144.16,"y":562.24},{"x":131.66,"y":562.24}]},"line":36,"tag":""},{"description":" ","boundingPoly":{"vertices":[{"x":0.0,"y":0.0},{"x":0.0,"y":0.0},{"x":0.0,"y":0.0},{"x":0.0,"y":0.0}]},"line":-1,"tag":""},{"description":" ","boundingPoly":{"vertices":[{"x":0.0,"y":0.0},{"x":0.0,"y":0.0},{"x":0.0,"y":0.0},{"x":0.0,"y":0.0}]},"line":-1,"tag":""},{"description":"Aston","boundingPoly":{"vertices":[{"x":100.82,"y":565.15},{"x":126.89,"y":565.15},{"x":126.89,"y":576.19},{"x":100.82,"y":576.19}]},"line":37,"tag":""},{"description":"Martin/V8","boundingPoly":{"vertices":[{"x":129.25,"y":565.15},{"x":175.88,"y":565.15},{"x":175.88,"y":576.19},{"x":129.25,"y":576.19}]},"line":37,"tag":""},{"description":"Vantage","boundingPoly":{"vertices":[{"x":178.41,"y":565.15},{"x":215.25,"y":565.15},{"x":215.25,"y":576.19},{"x":178.41,"y":576.19}]},"line":37,"tag":""},{"description":"815-12-9380","boundingPoly":{"vertices":[{"x":316.85,"y":565.15},{"x":373.82,"y":565.15},{"x":373.82,"y":576.19},{"x":316.85,"y":576.19}]},"line":37,"tag":""},{"description":"22600","boundingPoly":{"vertices":[{"x":523.18,"y":565.15},{"x":551.08,"y":565.15},{"x":551.08,"y":576.19},{"x":523.18,"y":576.19}]},"line":37,"tag":""},{"description":"Country","boundingPoly":{"vertices":[{"x":109.82,"y":577.96},{"x":136.42,"y":577.96},{"x":136.42,"y":586.0},{"x":109.82,"y":586.0}]},"line":38,"tag":""},{"description":"of","boundingPoly":{"vertices":[{"x":138.26,"y":577.96},{"x":145.12,"y":577.96},{"x":145.12,"y":586.0},{"x":138.26,"y":586.0}]},"line":38,"tag":""},{"description":"origin:","boundingPoly":{"vertices":[{"x":146.9,"y":577.96},{"x":168.29,"y":577.96},{"x":168.29,"y":586.0},{"x":146.9,"y":586.0}]},"line":38,"tag":""},{"description":"Portugal","boundingPoly":{"vertices":[{"x":170.06,"y":577.96},{"x":197.57,"y":577.96},{"x":197.57,"y":586.0},{"x":170.06,"y":586.0}]},"line":38,"tag":""},{"description":" ","boundingPoly":{"vertices":[{"x":0.0,"y":0.0},{"x":0.0,"y":0.0},{"x":0.0,"y":0.0},{"x":0.0,"y":0.0}]},"line":-1,"tag":""},{"description":" ","boundingPoly":{"vertices":[{"x":0.0,"y":0.0},{"x":0.0,"y":0.0},{"x":0.0,"y":0.0},{"x":0.0,"y":0.0}]},"line":-1,"tag":""},{"description":"Color:","boundingPoly":{"vertices":[{"x":109.82,"y":587.68},{"x":129.77,"y":587.68},{"x":129.77,"y":595.72},{"x":109.82,"y":595.72}]},"line":39,"tag":""},{"description":"Black","boundingPoly":{"vertices":[{"x":131.66,"y":587.68},{"x":148.64,"y":587.68},{"x":148.64,"y":595.72},{"x":131.66,"y":595.72}]},"line":39,"tag":""},{"description":" ","boundingPoly":{"vertices":[{"x":0.0,"y":0.0},{"x":0.0,"y":0.0},{"x":0.0,"y":0.0},{"x":0.0,"y":0.0}]},"line":-1,"tag":""},{"description":" ","boundingPoly":{"vertices":[{"x":0.0,"y":0.0},{"x":0.0,"y":0.0},{"x":0.0,"y":0.0},{"x":0.0,"y":0.0}]},"line":-1,"tag":""},{"description":"Nissan/Frontier","boundingPoly":{"vertices":[{"x":100.82,"y":598.66},{"x":170.38,"y":598.66},{"x":170.38,"y":609.7},{"x":100.82,"y":609.7}]},"line":40,"tag":"line-no","instance":1},{"description":"146-53-6874","boundingPoly":{"vertices":[{"x":316.85,"y":598.66},{"x":373.82,"y":598.66},{"x":373.82,"y":609.7},{"x":316.85,"y":609.7}]},"line":40,"tag":"description","instance":1},{"description":"33600","boundingPoly":{"vertices":[{"x":523.18,"y":598.66},{"x":551.08,"y":598.66},{"x":551.08,"y":609.7},{"x":523.18,"y":609.7}]},"line":40,"tag":"item-po-no","instance":1},{"description":"Country","boundingPoly":{"vertices":[{"x":109.82,"y":611.47},{"x":136.42,"y":611.47},{"x":136.42,"y":619.51},{"x":109.82,"y":619.51}]},"line":41,"tag":"line-no","instance":2},{"description":"of","boundingPoly":{"vertices":[{"x":138.26,"y":611.47},{"x":145.12,"y":611.47},{"x":145.12,"y":619.51},{"x":138.26,"y":619.51}]},"line":41,"tag":"line-no","instance":2},{"description":"origin:","boundingPoly":{"vertices":[{"x":146.9,"y":611.47},{"x":168.29,"y":611.47},{"x":168.29,"y":619.51},{"x":146.9,"y":619.51}]},"line":41,"tag":"line-no","instance":2},{"description":"France","boundingPoly":{"vertices":[{"x":170.06,"y":611.47},{"x":191.94,"y":611.47},{"x":191.94,"y":619.51},{"x":170.06,"y":619.51}]},"line":41,"tag":"line-no","instance":2},{"description":" ","boundingPoly":{"vertices":[{"x":0.0,"y":0.0},{"x":0.0,"y":0.0},{"x":0.0,"y":0.0},{"x":0.0,"y":0.0}]},"line":-1,"tag":""},{"description":" ","boundingPoly":{"vertices":[{"x":0.0,"y":0.0},{"x":0.0,"y":0.0},{"x":0.0,"y":0.0},{"x":0.0,"y":0.0}]},"line":-1,"tag":""},{"description":"Color:","boundingPoly":{"vertices":[{"x":109.82,"y":621.19},{"x":129.77,"y":621.19},{"x":129.77,"y":629.23},{"x":109.82,"y":629.23}]},"line":42,"tag":"line-no","instance":2},{"description":"Red","boundingPoly":{"vertices":[{"x":131.66,"y":621.19},{"x":144.16,"y":621.19},{"x":144.16,"y":629.23},{"x":131.66,"y":629.23}]},"line":42,"tag":"line-no","instance":2},{"description":" ","boundingPoly":{"vertices":[{"x":0.0,"y":0.0},{"x":0.0,"y":0.0},{"x":0.0,"y":0.0},{"x":0.0,"y":0.0}]},"line":-1,"tag":""},{"description":" ","boundingPoly":{"vertices":[{"x":0.0,"y":0.0},{"x":0.0,"y":0.0},{"x":0.0,"y":0.0},{"x":0.0,"y":0.0}]},"line":-1,"tag":""},{"description":"Mitsubishi/Endeavor","boundingPoly":{"vertices":[{"x":100.82,"y":632.02},{"x":194.05,"y":632.02},{"x":194.05,"y":643.06},{"x":100.82,"y":643.06}]},"line":43,"tag":""},{"description":"707-42-6202","boundingPoly":{"vertices":[{"x":316.85,"y":632.02},{"x":373.82,"y":632.02},{"x":373.82,"y":643.06},{"x":316.85,"y":643.06}]},"line":43,"tag":""},{"description":"18500","boundingPoly":{"vertices":[{"x":523.18,"y":632.02},{"x":551.08,"y":632.02},{"x":551.08,"y":643.06},{"x":523.18,"y":643.06}]},"line":43,"tag":""},{"description":"Country","boundingPoly":{"vertices":[{"x":109.82,"y":644.83},{"x":136.42,"y":644.83},{"x":136.42,"y":652.87},{"x":109.82,"y":652.87}]},"line":44,"tag":""},{"description":"of","boundingPoly":{"vertices":[{"x":138.26,"y":644.83},{"x":145.12,"y":644.83},{"x":145.12,"y":652.87},{"x":138.26,"y":652.87}]},"line":44,"tag":""},{"description":"origin:","boundingPoly":{"vertices":[{"x":146.9,"y":644.83},{"x":168.29,"y":644.83},{"x":168.29,"y":652.87},{"x":146.9,"y":652.87}]},"line":44,"tag":""},{"description":"Germany","boundingPoly":{"vertices":[{"x":170.18,"y":644.83},{"x":199.98,"y":644.83},{"x":199.98,"y":652.87},{"x":170.18,"y":652.87}]},"line":44,"tag":""},{"description":" ","boundingPoly":{"vertices":[{"x":0.0,"y":0.0},{"x":0.0,"y":0.0},{"x":0.0,"y":0.0},{"x":0.0,"y":0.0}]},"line":-1,"tag":""},{"description":" ","boundingPoly":{"vertices":[{"x":0.0,"y":0.0},{"x":0.0,"y":0.0},{"x":0.0,"y":0.0},{"x":0.0,"y":0.0}]},"line":-1,"tag":""},{"description":"Color:","boundingPoly":{"vertices":[{"x":109.82,"y":654.67},{"x":129.77,"y":654.67},{"x":129.77,"y":662.71},{"x":109.82,"y":662.71}]},"line":45,"tag":""},{"description":"Red","boundingPoly":{"vertices":[{"x":131.66,"y":654.67},{"x":144.16,"y":654.67},{"x":144.16,"y":662.71},{"x":131.66,"y":662.71}]},"line":45,"tag":""},{"description":" ","boundingPoly":{"vertices":[{"x":0.0,"y":0.0},{"x":0.0,"y":0.0},{"x":0.0,"y":0.0},{"x":0.0,"y":0.0}]},"line":-1,"tag":""},{"description":" ","boundingPoly":{"vertices":[{"x":0.0,"y":0.0},{"x":0.0,"y":0.0},{"x":0.0,"y":0.0},{"x":0.0,"y":0.0}]},"line":-1,"tag":""},{"description":"Mazda/B-Series","boundingPoly":{"vertices":[{"x":100.82,"y":665.5},{"x":171.24,"y":665.5},{"x":171.24,"y":676.54},{"x":100.82,"y":676.54}]},"line":46,"tag":""},{"description":"Plus","boundingPoly":{"vertices":[{"x":173.67,"y":665.5},{"x":192.01,"y":665.5},{"x":192.01,"y":676.54},{"x":173.67,"y":676.54}]},"line":46,"tag":""},{"description":"348-38-7014","boundingPoly":{"vertices":[{"x":316.85,"y":665.5},{"x":373.82,"y":665.5},{"x":373.82,"y":676.54},{"x":316.85,"y":676.54}]},"line":46,"tag":""},{"description":"40200","boundingPoly":{"vertices":[{"x":523.18,"y":665.5},{"x":551.08,"y":665.5},{"x":551.08,"y":676.54},{"x":523.18,"y":676.54}]},"line":46,"tag":""},{"description":"Tel:","boundingPoly":{"vertices":[{"x":108.02,"y":722.83},{"x":122.02,"y":722.83},{"x":122.02,"y":731.45},{"x":108.02,"y":731.45}]},"line":47,"tag":""},{"description":"+49","boundingPoly":{"vertices":[{"x":124.58,"y":723.06},{"x":140.53,"y":723.06},{"x":140.53,"y":732.2},{"x":124.58,"y":732.2}]},"line":47,"tag":""},{"description":"8031","boundingPoly":{"vertices":[{"x":143.06,"y":723.06},{"x":161.74,"y":723.06},{"x":161.74,"y":732.2},{"x":143.06,"y":732.2}]},"line":47,"tag":""},{"description":"32761","boundingPoly":{"vertices":[{"x":164.28,"y":723.06},{"x":187.67,"y":723.06},{"x":187.67,"y":732.2},{"x":164.28,"y":732.2}]},"line":47,"tag":""},{"description":"Fax:","boundingPoly":{"vertices":[{"x":108.02,"y":736.51},{"x":125.27,"y":736.51},{"x":125.27,"y":745.13},{"x":108.02,"y":745.13}]},"line":48,"tag":""},{"description":"+49","boundingPoly":{"vertices":[{"x":127.82,"y":736.74},{"x":143.77,"y":736.74},{"x":143.77,"y":745.88},{"x":127.82,"y":745.88}]},"line":48,"tag":""},{"description":"8031","boundingPoly":{"vertices":[{"x":146.3,"y":736.74},{"x":164.98,"y":736.74},{"x":164.98,"y":745.88},{"x":146.3,"y":745.88}]},"line":48,"tag":""},{"description":"32761","boundingPoly":{"vertices":[{"x":167.52,"y":736.74},{"x":190.91,"y":736.74},{"x":190.91,"y":745.88},{"x":167.52,"y":745.88}]},"line":48,"tag":""},{"description":"Email:","boundingPoly":{"vertices":[{"x":257.93,"y":722.83},{"x":283.35,"y":722.83},{"x":283.35,"y":731.45},{"x":257.93,"y":731.45}]},"line":47,"tag":""},{"description":"contact@neid.de","boundingPoly":{"vertices":[{"x":285.89,"y":723.06},{"x":351.31,"y":723.06},{"x":351.31,"y":732.2},{"x":285.89,"y":732.2}]},"line":47,"tag":""},{"description":"Web:","boundingPoly":{"vertices":[{"x":257.93,"y":736.51},{"x":281.07,"y":736.51},{"x":281.07,"y":745.13},{"x":257.93,"y":745.13}]},"line":48,"tag":""},{"description":"https://www.neid.de","boundingPoly":{"vertices":[{"x":283.61,"y":736.74},{"x":365.45,"y":736.74},{"x":365.45,"y":745.88},{"x":283.61,"y":745.88}]},"line":48,"tag":""},{"description":"Invoice","boundingPoly":{"vertices":[{"x":52.04,"y":255.89},{"x":52.04,"y":146.23},{"x":81.7,"y":146.23},{"x":81.7,"y":255.89}]},"line":49,"tag":""},{"description":"4405","boundingPoly":{"vertices":[{"x":52.04,"y":137.42},{"x":52.04,"y":68.79},{"x":81.7,"y":68.79},{"x":81.7,"y":137.42}]},"line":49,"tag":"invoice-no"}]}]}